pegghy_back/__init__.py
pegghy_back/app.py
pegghy_back/py.typed
pegghy_back/routes/blueprint_pegghy.py
pegghy_back/routes/schemas/__init__.py
pegghy_back/routes/schemas/healthcheck.json
pegghy_back/routes/schemas/healthcheck.py
pegghy_back-1.1.0.dist-info/licenses/LICENSE
pegghy_back-1.1.0.dist-info/METADATA
pegghy_back-1.1.0.dist-info/WHEEL
pegghy_back-1.1.0.dist-info/entry_points.txt
pegghy_back-1.1.0.dist-info/top_level.txt
pegghy_back-1.1.0.dist-info/RECORD
