Metadata-Version: 2.4
Name: pegghy_back
Version: 1.1.0
Author-email: Geode-solutions <team-web@geode-solutions.com>
Project-URL: Homepage, https://github.com/Geode-solutions/PEGGHy-back
Project-URL: Bug Tracker, https://github.com/Geode-solutions/PEGGHy-back/issues
Classifier: Programming Language :: Python :: 3
Classifier: License :: OSI Approved :: MIT License
Classifier: Operating System :: OS Independent
Requires-Python: >=3.8
License-File: LICENSE
Requires-Dist: opengeodeweb-back==5.*,>=5.15.0
Dynamic: license-file
